matplatex/__about__.py
matplatex/__init__.py
matplatex/journal_settings.py
matplatex/latex_input.py
matplatex/settings.py
matplatex/string_replacements.py
matplatex/tools.py
matplatex/ui.py
matplatex-0.9.6.dist-info/METADATA
matplatex-0.9.6.dist-info/WHEEL
matplatex-0.9.6.dist-info/licenses/COPYING
matplatex-0.9.6.dist-info/RECORD
