Metadata-Version: 2.4
Name: matplatex
Version: 0.9.6
Summary: A package to save matplotlib figures for easy inclusion in LaTeX.
Project-URL: GitHub, https://github.com/johashei/matplatex
Author-email: Johannes Sørby Heines <j.s.heines@protonmail.ch>
License-File: COPYING
Keywords: LaTeX,matplotlib,pdf_tex
Classifier: Development Status :: 4 - Beta
Classifier: Intended Audience :: Science/Research
Classifier: License :: OSI Approved :: GNU General Public License v3 or later (GPLv3+)
Classifier: Operating System :: OS Independent
Classifier: Programming Language :: Python :: 3.10
Classifier: Topic :: Multimedia :: Graphics :: Graphics Conversion
Classifier: Topic :: Scientific/Engineering :: Visualization
Classifier: Topic :: Text Processing :: Markup :: LaTeX
Requires-Python: >=3.10
Requires-Dist: beartype
Requires-Dist: matplotlib>=3.5
